{
  "main": {
    "id": "71586ee6a7741902",
    "type": "split",
    "children": [
      {
        "id": "9ca5b7a45eb2f014",
        "type": "tabs",
        "children": [
          {
            "id": "d47248c9f8f5f34e",
            "type": "leaf",
            "state": {
              "type": "empty",
              "state": {}
            }
          },
          {
            "id": "3b698ced2f040017",
            "type": "leaf",
            "state": {
              "type": "empty",
              "state": {}
            }
          }
        ],
        "currentTab": 1
      }
    ],
    "direction": "vertical"
  },
  "left": {
    "id": "65e81aeefe2807f5",
    "type": "split",
    "children": [
      {
        "id": "929bb6db828b3767",
        "type": "tabs",
        "children": [
          {
            "id": "621f7881cd57b9d7",
            "type": "leaf",
            "state": {
              "type": "file-explorer",
              "state": {
                "sortOrder": "alphabetical"
              }
            }
          },
          {
            "id": "39d64f349efded23",
            "type": "leaf",
            "state": {
              "type": "search",
              "state": {
                "query": "",
                "matchingCase": false,
                "explainSearch": false,
                "collapseAll": false,
                "extraContext": false,
                "sortOrder": "alphabetical"
              }
            }
          },
          {
            "id": "36aee3e7f86fbd6e",
            "type": "leaf",
            "state": {
              "type": "bookmarks",
              "state": {}
            }
          }
        ]
      }
    ],
    "direction": "horizontal",
    "width": 202.5
  },
  "right": {
    "id": "7557bcfb297e1979",
    "type": "split",
    "children": [
      {
        "id": "34e318030e7aed08",
        "type": "tabs",
        "children": [
          {
            "id": "f0e02a3fa3ce96bb",
            "type": "leaf",
            "state": {
              "type": "backlink",
              "state": {
                "collapseAll": false,
                "extraContext": false,
                "sortOrder": "alphabetical",
                "showSearch": false,
                "searchQuery": "",
                "backlinkCollapsed": false,
                "unlinkedCollapsed": true
              }
            }
          },
          {
            "id": "b051b1108597ada7",
            "type": "leaf",
            "state": {
              "type": "outgoing-link",
              "state": {
                "linksCollapsed": false,
                "unlinkedCollapsed": true
              }
            }
          },
          {
            "id": "2f1384551de29839",
            "type": "leaf",
            "state": {
              "type": "tag",
              "state": {
                "sortOrder": "frequency",
                "useHierarchy": true
              }
            }
          },
          {
            "id": "5900e0aea4ce7841",
            "type": "leaf",
            "state": {
              "type": "outline",
              "state": {}
            }
          }
        ]
      }
    ],
    "direction": "horizontal",
    "width": 300,
    "collapsed": true
  },
  "left-ribbon": {
    "hiddenItems": {
      "switcher:Open quick switcher": false,
      "graph:Open graph view": false,
      "canvas:Create new canvas": false,
      "daily-notes:Open today's daily note": false,
      "templates:Insert template": false,
      "command-palette:Open command palette": false
    }
  },
  "active": "3b698ced2f040017",
  "lastOpenFiles": [
    "SSC/history.md",
    "SSC/images/Pasted image 20240923162403.png",
    "SSC/history - 副本.md",
    "SSC/images/Pasted image 20240923144702.png",
    "Windows Terminal Commands.md",
    "Linux Commands.md",
    "Calculus/ch11 Infinite Sequences and Series/08 Power Series.md",
    "Calculus/ch11 Infinite Sequences and Series/10 Representations of Functions as Power Series.md",
    "Calculus/ch11 Infinite Sequences and Series/images/Pasted image 20240923081128.png",
    "Calculus/ch11 Infinite Sequences and Series/images/Pasted image 20240923081041.png",
    "Calculus/ch11 Infinite Sequences and Series/images/Pasted image 20240923081022.png",
    "Calculus/ch11 Infinite Sequences and Series/images/Pasted image 20240923073523.png",
    "Calculus/ch11 Infinite Sequences and Series/images/Pasted image 20240923073342.png",
    "Calculus/ch11 Infinite Sequences and Series/images/Pasted image 20240923073236.png",
    "Calculus/ch11 Infinite Sequences and Series/images/Pasted image 20240923073225.png",
    "Calculus/ch11 Infinite Sequences and Series/images/Pasted image 20240923073008.png",
    "Calculus/ch11 Infinite Sequences and Series/06 Absolute Convergence and the Ratio and Root Tests.md",
    "Calculus/ch11 Infinite Sequences and Series/07 Strategy for Testing Series.md",
    "Calculus/ch11 Infinite Sequences and Series/05 Alternating Series.md",
    "Calculus/ch11 Infinite Sequences and Series/03 The Integral Test and Estimates of Sums.md",
    "Calculus/ch11 Infinite Sequences and Series/02 Series.md",
    "Calculus/ch11 Infinite Sequences and Series/01 Sequences.md",
    "Calculus/ch11 Infinite Sequences and Series/04 The Comparison Tests.md",
    "Vim Commands.md",
    "Git Commands.md",
    "Powershell Commands.md",
    "blog.md",
    "recommendSite.md",
    "ubuntu玄学问题.md",
    "深度学习小本本.md",
    "2024/July/2024-07-24.md",
    "2024/July/2024-07-29.md",
    "2024/July/2024-07-31.md",
    "2024-08-08.md",
    "2024/July/2024-07-01.md",
    "SSC/images",
    "SSC",
    "Calculus/ch11 Infinite Sequences and Series/images",
    "Calculus/ch11 Infinite Sequences and Series",
    "images",
    "Calculus/ch09 Differential Equations/images",
    "Calculus/ch09 Differential Equations",
    "d2l/19 卷积层",
    "d2l/12 权重衰退",
    "d2l/11 模型选择 + 过拟合和欠拟合/images",
    "Untitled.canvas"
  ]
}